bento_mdf/__init__.py
bento_mdf/diff.py
bento_mdf/diff_summary.py
bento_mdf/loader.py
bento_mdf/validator.py
bento_mdf/bin/diff_mdfs.py
bento_mdf/bin/load_mdf.py
bento_mdf/bin/val_mdf.py
bento_mdf/bin/val_mdf_cdes.py
bento_mdf/mdf/__init__.py
bento_mdf/mdf/convert.py
bento_mdf/mdf/convert.pyi
bento_mdf/mdf/reader.py
bento_mdf/mdf/validator.py
bento_mdf/mdf/vtypes.py
bento_mdf/mdf/writer.py
bento_mdf/mdf/templates/pymodel.py.jinja2
bento_mdf-0.12.1.dist-info/METADATA
bento_mdf-0.12.1.dist-info/WHEEL
bento_mdf-0.12.1.dist-info/entry_points.txt
bento_mdf-0.12.1.dist-info/RECORD
