Metadata-Version: 2.4
Name: bento-mdf
Version: 0.12.1
Summary: Python driver/validator for Bento Model Description Format
Project-URL: Homepage, https://github.com/CBIIT/bento-mdf
Project-URL: Bug Tracker, https://github.com/CBIIT/bento-mdf/issues
Author-email: "Mark A. Jensen" <mark.jensen@nih.gov>, "Nelson W. Moore" <nelson.moore@essential-soft.com>
Classifier: License :: OSI Approved :: Apache Software License
Classifier: Programming Language :: Python :: 3
Requires-Python: >=3.10
Requires-Dist: annotated-types<1.0.0,>=0.7.0
Requires-Dist: bento-meta>=0.3.1
Requires-Dist: certifi>=2025.4.26
Requires-Dist: cryptography<46.0.0,>=45.0.3
Requires-Dist: delfick-project==0.7.9
Requires-Dist: hatchling>=1.28.0
Requires-Dist: jinja2==3.1.6
Requires-Dist: jsonschema<5.0.0,>=4.17.3
Requires-Dist: pydantic>=2.10.4
Requires-Dist: pyyaml>=6.0.1
Requires-Dist: requests<3.0.0,>=2.32.4
Requires-Dist: setuptools<81.0.0,>=80.9.0
Requires-Dist: tornado<7.0.0,>=6.5.1
Requires-Dist: tqdm<5.0.0,>=4.64.1
Requires-Dist: urllib3<3.0.0,>=2.5.0
Provides-Extra: dev
Requires-Dist: jupyter<2.0.0,>=1.0.0; extra == 'dev'
Requires-Dist: jupyterlab<5.0.0,>=4.4.9; extra == 'dev'
Requires-Dist: myst-nb<2.0.0,>=1.0.0; extra == 'dev'
Requires-Dist: pytest-cov<5.0.0,>=4.0.0; extra == 'dev'
Requires-Dist: pytest<8.0.0,>=7.2.1; extra == 'dev'
Requires-Dist: python-semantic-release<8.0.0,>=7.33.0; extra == 'dev'
Requires-Dist: sphinx-autoapi<4.0.0,>=3.4.0; extra == 'dev'
Requires-Dist: sphinx-rtd-theme<4.0.0,>=3.0.2; extra == 'dev'
Requires-Dist: sphinx<9.0.0,>=8.1.3; extra == 'dev'
